s1reader/__init__.py
s1reader/get_xml_boundary.py
s1reader/s1_annotation.py
s1reader/s1_burst_id.py
s1reader/s1_burst_slc.py
s1reader/s1_etad.py
s1reader/s1_info.py
s1reader/s1_orbit.py
s1reader/s1_reader.py
s1reader/version.py
s1reader/data/sentinel1_track_burst_id.txt
s1reader/data/aux_cal/S1A_AUX_CAL_V20140406T133000_G20190626T100036.SAFE.zip
s1reader/data/aux_cal/S1A_AUX_CAL_V20140616T133500_G20190626T100133.SAFE.zip
s1reader/data/aux_cal/S1A_AUX_CAL_V20140908T000000_G20190626T100201.SAFE.zip
s1reader/data/aux_cal/S1A_AUX_CAL_V20150519T120000_G20190626T100229.SAFE.zip
s1reader/data/aux_cal/S1A_AUX_CAL_V20150722T120000_G20190626T100253.SAFE.zip
s1reader/data/aux_cal/S1A_AUX_CAL_V20160627T000000_G20190626T100501.SAFE.zip
s1reader/data/aux_cal/S1A_AUX_CAL_V20171017T080000_G20210104T141000.SAFE.zip
s1reader/data/aux_cal/S1A_AUX_CAL_V20190228T092500_G20210104T141310.SAFE.zip
s1reader/data/aux_cal/S1B_AUX_CAL_V20160422T000000_G20210104T140113.SAFE.zip
s1reader/data/aux_cal/S1B_AUX_CAL_V20190514T090000_G20210104T140612.SAFE.zip
s1reader/utils/__init__.py
s1reader/utils/plot_bursts.py
sentinel1_reader-0.1.5.dist-info/LICENSE
sentinel1_reader-0.1.5.dist-info/METADATA
sentinel1_reader-0.1.5.dist-info/WHEEL
sentinel1_reader-0.1.5.dist-info/entry_points.txt
sentinel1_reader-0.1.5.dist-info/top_level.txt
sentinel1_reader-0.1.5.dist-info/RECORD
