Metadata-Version: 2.1
Name: sentinel1-reader
Version: 0.1.5
Summary: A Sentinel-1 reader for ISCE3
Home-page: https://github.com/opera-adt/s1-reader
Classifier: Development Status :: 2 - Pre-Alpha
Classifier: Intended Audience :: Science/Research
Classifier: Programming Language :: Python :: 3
Classifier: Operating System :: OS Independent
Requires-Python: >=3.9
License-File: LICENSE
Requires-Dist: setuptools
Requires-Dist: importlib-resources
